xmessagebus/__init__.py
xmessagebus/message_bus.py
xmessagebus-0.1.14.dist-info/METADATA
xmessagebus-0.1.14.dist-info/WHEEL
xmessagebus-0.1.14.dist-info/licenses/LICENSE
xmessagebus-0.1.14.dist-info/RECORD
