Metadata-Version: 2.4
Name: xmessagebus
Version: 0.1.14
Summary: A package to publish and receive messages
Project-URL: Homepage, https://github.com/shawn-peng/xmessagebus
Project-URL: Bug Tracker, https://github.com/shawn-peng/xmessagebus/issues
Author-email: Yisu Peng <yisupeng@gmail.com>
License-File: LICENSE
Classifier: License :: OSI Approved :: MIT License
Classifier: Operating System :: OS Independent
Classifier: Programming Language :: Python :: 3
Requires-Python: >=3.7
Requires-Dist: absl-py
Requires-Dist: xasyncio>=0.2.12
